[
    {
        "image": "./assets/cycling.png",
        "name": "cycling"
    },
    {
        "image": "./assets/golf.png",
        "name": "golf"
    },
    {
        "image": "./assets/badminton.png",
        "name": "badminton"
    },
    {
        "image": "./assets/ice-skate.png",
        "name": "ice-skate"
    },
    {
        "image": "./assets/rugby-ball.png",
        "name": "rugby-ball"
    },
    {
        "image": "./assets/skateboard.png",
        "name": "skateboard"
    },
    {
        "image": "./assets/ski.png",
        "name": "ski"
    },
    {
        "image": "./assets/ballet.png",
        "name": "ballet"
    },
    {
        "image": "./assets/boxing.png",
        "name": "boxing"
    },
    {
        "image": "./assets/soccer-ball.png",
        "name": "soccer-ball"
    },
    {
        "image": "./assets/table-tennis.png",
        "name": "table-tennis"
    },
    {
        "image": "./assets/tennis.png",
        "name": "tennis"
    }
]
